[
  {
    "title": "【応援上映】【ScreenX】も～っと煌めく！KING OF PRISM -Dramatic PRISM.1-",
    "screenName": "シアター３",
    "startTime": "2024-11-29T07:30:00.000Z",
    "endTime": "2024-11-29T08:45:00.000Z",
    "status": "-販売終了"
  },
  {
    "title": "【応援上映】【ScreenX】も～っと煌めく！KING OF PRISM -Dramatic PRISM.1-",
    "screenName": "シアター３",
    "startTime": "2024-11-30T08:30:00.000Z",
    "endTime": "2024-11-30T09:45:00.000Z",
    "status": "◎予約/購入"
  },
  {
    "title": "【応援上映】【ScreenX】も～っと煌めく！KING OF PRISM -Dramatic PRISM.1-",
    "screenName": "シアター３",
    "startTime": "2024-12-01T07:30:00.000Z",
    "endTime": "2024-12-01T08:45:00.000Z",
    "status": "◎予約/購入"
  },
  {
    "title": "【応援上映】【ScreenX】も～っと煌めく！KING OF PRISM -Dramatic PRISM.1-",
    "screenName": "シアター３",
    "startTime": "2024-12-02T07:30:00.000Z",
    "endTime": "2024-12-02T08:45:00.000Z",
    "status": "-販売対象外"
  },
  {
    "title": "【応援上映】【ScreenX】も～っと煌めく！KING OF PRISM -Dramatic PRISM.1-",
    "screenName": "シアター３",
    "startTime": "2024-12-03T07:30:00.000Z",
    "endTime": "2024-12-03T08:45:00.000Z",
    "status": "-販売対象外"
  },
  {
    "title": "【応援上映】【ScreenX】も～っと煌めく！KING OF PRISM -Dramatic PRISM.1-",
    "screenName": "シアター３",
    "startTime": "2024-12-04T07:30:00.000Z",
    "endTime": "2024-12-04T08:45:00.000Z",
    "status": "-販売対象外"
  },
  {
    "title": "【応援上映】【ScreenX】も～っと煌めく！KING OF PRISM -Dramatic PRISM.1-",
    "screenName": "シアター３",
    "startTime": "2024-12-05T07:30:00.000Z",
    "endTime": "2024-12-05T08:45:00.000Z",
    "status": "-販売対象外"
  }
]