[
  {
    "title": "[応援上映]【-∞ラブThanks Week-】KING OF PRISM -Dramatic PRISM.1-",
    "screenName": "シアター６",
    "startTime": "2024-11-23T10:25:00.000Z",
    "endTime": "2024-11-23T11:35:00.000Z",
    "status": "◎予約/購入"
  },
  {
    "title": "[応援上映]【-∞ラブThanks Week-】KING OF PRISM -Dramatic PRISM.1-",
    "screenName": "シアター６",
    "startTime": "2024-11-24T10:25:00.000Z",
    "endTime": "2024-11-24T11:35:00.000Z",
    "status": "◎予約/購入"
  },
  {
    "title": "[応援上映]【-∞ラブThanks Week-】KING OF PRISM -Dramatic PRISM.1-",
    "screenName": "シアター６",
    "startTime": "2024-11-25T10:25:00.000Z",
    "endTime": "2024-11-25T11:35:00.000Z",
    "status": "◎予約/購入"
  },
  {
    "title": "[応援上映]【-∞ラブThanks Week-】KING OF PRISM -Dramatic PRISM.1-",
    "screenName": "シアター６",
    "startTime": "2024-11-26T10:25:00.000Z",
    "endTime": "2024-11-26T11:35:00.000Z",
    "status": "-販売対象外"
  },
  {
    "title": "[応援上映]【-∞ラブThanks Week-】KING OF PRISM -Dramatic PRISM.1-",
    "screenName": "シアター６",
    "startTime": "2024-11-27T10:25:00.000Z",
    "endTime": "2024-11-27T11:35:00.000Z",
    "status": "-販売対象外"
  },
  {
    "title": "[応援上映]【-∞ラブThanks Week-】KING OF PRISM -Dramatic PRISM.1-",
    "screenName": "シアター６",
    "startTime": "2024-11-28T10:25:00.000Z",
    "endTime": "2024-11-28T11:35:00.000Z",
    "status": "-販売対象外"
  }
]