[
  {
    "title": "[4DX] プリズムスタァ応援上映『も～っと煌めく!KING OF PRISM -Dramatic PRISM.1-』4DX2D",
    "screenName": "1screen",
    "startTime": "2024-11-12T10:55:00.000Z",
    "endTime": "2024-11-12T12:14:00.000Z",
    "status": "○"
  },
  {
    "title": "[4DX] プリズムスタァ応援上映『も～っと煌めく!KING OF PRISM -Dramatic PRISM.1-』4DX2D",
    "screenName": "1screen",
    "startTime": "2024-11-13T10:55:00.000Z",
    "endTime": "2024-11-13T12:14:00.000Z",
    "status": "○"
  },
  {
    "title": "[4DX] プリズムスタァ応援上映『も～っと煌めく!KING OF PRISM -Dramatic PRISM.1-』4DX2D",
    "screenName": "1screen",
    "startTime": "2024-11-14T10:55:00.000Z",
    "endTime": "2024-11-14T12:14:00.000Z",
    "status": "○"
  }
]