[
  {
    "title": "[4DX] 【生誕ウィーク】応援上映「も～っとつながる！KING OF PRISM-YEC-」ルート1オバレ 4DX2D",
    "screenName": "11screen",
    "startTime": "2025-09-25T00:20:00.000Z",
    "endTime": "2025-09-25T01:38:00.000Z",
    "status": "販売対象外"
  },
  {
    "title": "[4DX] も～っとつながる!KING OF PRISM-Your Endless Call- route5 22世紀　4DX2D＜応援＞",
    "screenName": "11screen",
    "startTime": "2025-09-26T09:20:00.000Z",
    "endTime": "2025-09-26T10:36:00.000Z",
    "status": "○"
  },
  {
    "title": "[4DX] も～っとつながる!KING OF PRISM-Your Endless Call- route5 22世紀　4DX2D＜応援＞",
    "screenName": "11screen",
    "startTime": "2025-09-27T09:20:00.000Z",
    "endTime": "2025-09-27T10:36:00.000Z",
    "status": "○"
  },
  {
    "title": "[4DX] も～っとつながる!KING OF PRISM-Your Endless Call- route5 22世紀　4DX2D＜応援＞",
    "screenName": "11screen",
    "startTime": "2025-09-28T09:20:00.000Z",
    "endTime": "2025-09-28T10:36:00.000Z",
    "status": "○"
  },
  {
    "title": "[4DX] も～っとつながる!KING OF PRISM-Your Endless Call- route5 22世紀　4DX2D＜応援＞",
    "screenName": "11screen",
    "startTime": "2025-09-29T09:20:00.000Z",
    "endTime": "2025-09-29T10:36:00.000Z",
    "status": "販売期間外"
  },
  {
    "title": "[4DX] も～っとつながる!KING OF PRISM-Your Endless Call- route5 22世紀　4DX2D＜応援＞",
    "screenName": "11screen",
    "startTime": "2025-09-30T09:20:00.000Z",
    "endTime": "2025-09-30T10:36:00.000Z",
    "status": "販売期間外"
  },
  {
    "title": "[4DX] 「も～っとつながる!KING OF PRISM」大ヒット御礼打ち上げ舞台挨拶ライブビューイング4DX応援上映",
    "screenName": "11screen",
    "startTime": "2025-10-01T09:20:00.000Z",
    "endTime": "2025-10-01T11:10:00.000Z",
    "status": "販売期間外"
  },
  {
    "title": "[4DX] も～っとつながる!KING OF PRISM-Your Endless Call- route5 22世紀　4DX2D＜応援＞",
    "screenName": "11screen",
    "startTime": "2025-10-02T09:20:00.000Z",
    "endTime": "2025-10-02T10:36:00.000Z",
    "status": "販売期間外"
  }
]