[
  {
    "title": "[応援上映]KING OF PRISM -Dramatic PRISM.1-",
    "screenName": "シアター３",
    "startTime": "2024-12-12T06:30:00.000Z",
    "endTime": "2024-12-12T07:45:00.000Z",
    "status": "-販売終了"
  },
  {
    "title": "[応援上映]KING OF PRISM -Dramatic PRISM.1-",
    "screenName": "シアター８",
    "startTime": "2024-12-13T14:59:00.000Z",
    "endTime": "2024-12-13T14:59:00.000Z",
    "status": "◎予約/購入"
  },
  {
    "title": "[応援上映]KING OF PRISM -Dramatic PRISM.1-",
    "screenName": "シアター８",
    "startTime": "2024-12-14T14:59:00.000Z",
    "endTime": "2024-12-14T14:59:00.000Z",
    "status": "◎予約/購入"
  },
  {
    "title": "[応援上映]KING OF PRISM -Dramatic PRISM.1-",
    "screenName": "シアター８",
    "startTime": "2024-12-15T14:59:00.000Z",
    "endTime": "2024-12-15T14:59:00.000Z",
    "status": "-販売対象外"
  },
  {
    "title": "[応援上映]KING OF PRISM -Dramatic PRISM.1-",
    "screenName": "シアター８",
    "startTime": "2024-12-16T13:05:00.000Z",
    "endTime": "2024-12-16T14:20:00.000Z",
    "status": "-販売対象外"
  },
  {
    "title": "[応援上映]KING OF PRISM -Dramatic PRISM.1-",
    "screenName": "シアター８",
    "startTime": "2024-12-17T14:20:00.000Z",
    "endTime": "2024-12-17T14:59:00.000Z",
    "status": "-販売対象外"
  },
  {
    "title": "[応援上映]KING OF PRISM -Dramatic PRISM.1-",
    "screenName": "シアター８",
    "startTime": "2024-12-18T14:59:00.000Z",
    "endTime": "2024-12-18T14:59:00.000Z",
    "status": "-販売対象外"
  },
  {
    "title": "[応援上映]KING OF PRISM -Dramatic PRISM.1-",
    "screenName": "シアター８",
    "startTime": "2024-12-19T14:59:00.000Z",
    "endTime": "2024-12-19T14:59:00.000Z",
    "status": "-販売対象外"
  }
]